MANIFEST.in
README.txt
ez_setup.py
setup.py
thebops/__init__.py
thebops/tools/__init__.py
thebops/tools/tsvn.py
tsvn.egg-info/PKG-INFO
tsvn.egg-info/SOURCES.txt
tsvn.egg-info/dependency_links.txt
tsvn.egg-info/entry_points.txt
tsvn.egg-info/namespace_packages.txt
tsvn.egg-info/requires.txt
tsvn.egg-info/top_level.txt