Metadata-Version: 1.0
Name: tsvn
Version: 0.3.14
Summary: svn-like commandline interface to TortoiseSVN
Home-page: UNKNOWN
Author: Tobias Herp
Author-email: tobias.herp@gmx.net
License: GPL
Platform: UNKNOWN
